{"buyerId":"40003857687","buyerName":"AS \"Sadales tīkls\"","riskScore":100,"combinedScore":39,"combinedLevel":"yellow","layerScores":{"A":30,"B":0,"C":100,"D":0,"E":0,"G":100},"result":{"indicator":"B1","scope":"buyer","buyerId":"40003857687","status":"RiskNotFound","level":null,"score":0,"detail":{"buyerName":"AS \"Sadales tīkls\"","winnerChosenLots":541,"singleBidLots":52,"nationalAvg":0.2484,"flaggedLotIds":["268547","268548","385564","388144","388145","388147","388148","388149","398415","398428","398429","398430","398432","398433","398434","398435","398438","398444","398445","398447","398451","398452","398453","398456","398457","398458","398460","398461","398462","398464","398468","398683","398684","398687","398688","398689","398691","398692","398694","398695","398698","398699","398704","398710","398711","398712","401884","417143","420837","498061","498066","508412"],"singleBidRate":0.0961,"relativeRatio":0.387}},"b2":{"indicator":"B2","scope":"buyer","buyerId":"40003857687","status":"RiskNotFound","level":null,"score":0,"detail":{"buyerName":"AS \"Sadales tīkls\"","awardedLots":722,"basis":"value","distinctWinners":123,"hhi":0.047,"topWinnerShare":0.086,"topWinnerId":"40003511655","topWinnerName":"SIA \"Ditra Networks\"","totalAwardValue":413910037.64}},"a":{"indicator":"A","scope":"buyer","buyerId":"40003857687","status":"RiskFound","level":"yellow","score":30,"detail":{"buyerName":"AS \"Sadales tīkls\"","usableLots":105,"clusterCount":1,"clusters":[{"cpv4":"4523","members":[{"id":"436079","value":22132.149999999998,"date":"2025-05-16","winnerId":"49003000127","winnerName":"SIA \"TALSU SPRIEGUMS\"","sourceUrl":"https://www.eis.gov.lv/EKEIS/Supplier/Procurement/141609"},{"id":"438535","value":127384.62,"date":"2025-06-09","winnerId":"40003524433","winnerName":"SIA \"DELTA EM\"","sourceUrl":"https://www.eis.gov.lv/EKEIS/Supplier/Procurement/145149"},{"id":"445061","value":86691.59,"date":"2025-06-25","winnerId":"40003511655","winnerName":"SIA \"Ditra Networks\"","sourceUrl":"https://www.eis.gov.lv/EKEIS/Supplier/Procurement/144399"}],"count":3,"sum":236208.36,"threshold":170000,"sumRatio":1.39,"sameWinner":false,"nearThreshold":2,"from":"2025-05-16","to":"2025-06-25","level":"yellow"}]}},"c":{"indicator":"C","scope":"buyer","buyerId":"40003857687","status":"RiskFound","level":"red","score":100,"detail":{"buyerName":"AS \"Sadales tīkls\"","evaluatedLots":685,"maxZ":3.61,"priceFlags":[{"lotId":"403073","value":2641572,"cpv":"24000000-4","z":3.61,"obs":146,"sourceUrl":"https://www.eis.gov.lv/EKEIS/Supplier/Procurement/129677"},{"lotId":"498059","value":2681750,"cpv":"34115200-8","z":3.22,"obs":386,"sourceUrl":"https://www.eis.gov.lv/EKEIS/Supplier/Procurement/157815"},{"lotId":"388146","value":1915485,"cpv":"34100000-8","z":3.17,"obs":234,"sourceUrl":"https://www.eis.gov.lv/EKEIS/Supplier/Procurement/118710"},{"lotId":"399001","value":5400000,"cpv":"44212224-5","z":2.99,"obs":68,"sourceUrl":null},{"lotId":"480835","value":20572992,"cpv":"45000000-7","z":2.98,"obs":2680,"sourceUrl":"https://www.eis.gov.lv/EKEIS/Supplier/Procurement/82067"},{"lotId":"480834","value":20572992,"cpv":"45000000-7","z":2.98,"obs":2680,"sourceUrl":"https://www.eis.gov.lv/EKEIS/Supplier/Procurement/82067"},{"lotId":"480831","value":20572992,"cpv":"45000000-7","z":2.98,"obs":2680,"sourceUrl":"https://www.eis.gov.lv/EKEIS/Supplier/Procurement/82067"},{"lotId":"480829","value":20572992,"cpv":"45000000-7","z":2.98,"obs":2680,"sourceUrl":"https://www.eis.gov.lv/EKEIS/Supplier/Procurement/82067"},{"lotId":"480827","value":20572992,"cpv":"45000000-7","z":2.98,"obs":2680,"sourceUrl":"https://www.eis.gov.lv/EKEIS/Supplier/Procurement/82067"},{"lotId":"480822","value":20572992,"cpv":"45000000-7","z":2.98,"obs":2680,"sourceUrl":"https://www.eis.gov.lv/EKEIS/Supplier/Procurement/82067"},{"lotId":"481182","value":20572992,"cpv":"45000000-7","z":2.98,"obs":2680,"sourceUrl":"https://www.eis.gov.lv/EKEIS/Supplier/Procurement/82067"},{"lotId":"481628","value":20572992,"cpv":"45000000-7","z":2.98,"obs":2680,"sourceUrl":"https://www.eis.gov.lv/EKEIS/Supplier/Procurement/82067"},{"lotId":"492957","value":20572992,"cpv":"45000000-7","z":2.98,"obs":2680,"sourceUrl":"https://www.eis.gov.lv/EKEIS/Supplier/Procurement/82067"},{"lotId":"492950","value":20572992,"cpv":"45000000-7","z":2.98,"obs":2680,"sourceUrl":"https://www.eis.gov.lv/EKEIS/Supplier/Procurement/82067"},{"lotId":"499447","value":20572992,"cpv":"45000000-7","z":2.98,"obs":2680,"sourceUrl":"https://www.eis.gov.lv/EKEIS/Supplier/Procurement/82067"},{"lotId":"500986","value":20572992,"cpv":"45000000-7","z":2.98,"obs":2680,"sourceUrl":"https://www.eis.gov.lv/EKEIS/Supplier/Procurement/82067"},{"lotId":"516048","value":20572992,"cpv":"45000000-7","z":2.98,"obs":2680,"sourceUrl":"https://www.eis.gov.lv/EKEIS/Supplier/Procurement/82067"},{"lotId":"420853","value":2502000,"cpv":"31000000-6","z":2.8,"obs":189,"sourceUrl":"https://www.eis.gov.lv/EKEIS/Supplier/Procurement/103292"},{"lotId":"388144","value":1260000,"cpv":"34100000-8","z":2.79,"obs":234,"sourceUrl":"https://www.eis.gov.lv/EKEIS/Supplier/Procurement/118710"},{"lotId":"372664","value":5441480,"cpv":"45315300-1","z":2.73,"obs":171,"sourceUrl":"https://www.eis.gov.lv/EKEIS/Supplier/Procurement/119330"},{"lotId":"420837","value":2089540,"cpv":"31000000-6","z":2.69,"obs":189,"sourceUrl":"https://www.eis.gov.lv/EKEIS/Supplier/Procurement/125260"},{"lotId":"376756","value":4084949,"cpv":"45315300-1","z":2.56,"obs":171,"sourceUrl":"https://www.eis.gov.lv/EKEIS/Supplier/Procurement/116168"},{"lotId":"477757","value":1064700,"cpv":"34115200-8","z":2.46,"obs":386,"sourceUrl":"https://www.eis.gov.lv/EKEIS/Supplier/Procurement/157815"},{"lotId":"388151","value":865110,"cpv":"34100000-8","z":2.44,"obs":234,"sourceUrl":"https://www.eis.gov.lv/EKEIS/Supplier/Procurement/118710"},{"lotId":"498062","value":959520,"cpv":"34115200-8","z":2.37,"obs":386,"sourceUrl":"https://www.eis.gov.lv/EKEIS/Supplier/Procurement/157815"}]}},"e":{"indicator":"E","scope":"buyer","buyerId":"40003857687","status":"RiskNotFound","level":null,"score":0,"detail":{"buyerName":"AS \"Sadales tīkls\"","awardedLots":722,"nonCompetitiveLots":3,"nonCompetitiveShare":0.004,"flaggedLotIds":["398821","399001","508259"]}},"d":{"indicator":"D","scope":"buyer","buyerId":"40003857687","status":"RiskNotFound","level":null,"score":0,"detail":{"buyerName":"AS \"Sadales tīkls\"","evaluableAwards":706,"newWinnerAwards":0,"veryNewAwards":0,"newWinners":[]}},"g":{"indicator":"G","scope":"buyer","buyerId":"40003857687","status":"RiskFound","level":"red","score":100,"detail":{"buyerName":"AS \"Sadales tīkls\"","contracts":114,"modifiedContracts":64,"substantiveContracts":28,"substantiveRate":0.246,"byReasonCode":{"mod-nons":11,"mod-cir":34,"mod-rev":40,"mod-minv":27,"add-wss":28},"modifications":[{"procedureId":"385f5d22-74ba-4182-b6ba-bee7f0eb8605","buyerId":"40003857687","buyerName":"AS \"Sadales tīkls\"","cpv":"72224100-2","reasonCode":"add-wss","reasonDescription":"Nepieciešams izveidot augstas pieejamības komunikācijas arhitektūru","description":"Izmaksu palielinājums par 49 544,00 EUR, bez PVN, nosakot kopējās izmaksas līdz 2 096 644, 00 EUR  bez PVN. Projekta realizācijas gaitā nepieciešams izveidot augstas pieejamības komunikācijas arhitektūru. ","value":2047100,"winnerName":"Netcontrol SIA","sourceUrl":null,"date":null,"name":"Viedā elektrotīkla pārvaldības risinājuma ieviešana pilnveidojot Dispečervadības sistēmu"},{"procedureId":"c5ad8200-20ad-41ff-bea7-e0d40685420c","buyerId":"40003857687","buyerName":"AS \"Sadales tīkls\"","cpv":"45315300-1","reasonCode":"add-wss","reasonDescription":"Objekta īstenošanai nepieciešami papildu darbi un apjomi, kas nebija iekļauti sākotnējā tāmē","description":"Veikti grozījumi līguma tāmē, pievienojot papildus darbus, t.sk. ar tiem saistītos materiālus (sadalnes uzstādīšana un pieslēgšana) un palielinot kopējo summu par 6 328,62 EUR bez PVN un nosakot kopējo līguma summu 770 678,39  EUR bez PVN, kā arī veicot grozījumus Līguma Pielikumā Nr.1, izsakot to jaunā redakcijā.","value":770678.39,"winnerName":"Sabiedrība ar ierobežotu atbildību \"ELSANA\"","sourceUrl":null,"date":null,"name":"Pieejamās jaudas palielināšana A/st 24 \"Tēraudlietuve\", A/st 41 \"Olaine\" un A/st 74 \"Jāņaparks\""},{"procedureId":"6b2e6a2e-0fab-42df-bfe4-4652ab1bcb0e","buyerId":"40003857687","buyerName":"Akciju sabiedrība \"Sadales tīkls\"","cpv":"45231400-9","reasonCode":"add-wss","reasonDescription":"Līguma vispārīgo noteikumu 18.1., 21.5.punkts, SPSIL 66.panta trešās daļas 2.punkts, 66.panta ceturtā daļa","description":"Palielināta līguma summa par 1 750,21 EUR bez PVN, un grozīts līguma speciālo noteikumu\n3.1.punkts, samaksu par veiktajiem būvdarbiem nosakot 699 805,51 EUR bez PVN. Precizēts līguma pielikums - tāme.","value":699805.51,"winnerName":"Sabiedrība ar ierobežotu atbildību \"Hanza-elektro\"","sourceUrl":null,"date":null,"name":"Jaunas 20kV kabeļlīnijas izbūve pieejamās jaudas uzlabošanai Baldonē, Ķekavas novadā, un Tomes pagastā, Ogres novadā (IO-214062)"},{"procedureId":"640be8b5-a9b1-48a4-be1a-334104ccbc80","buyerId":"40003857687","buyerName":"AS \"Sadales tīkls\"","cpv":"45231400-9","reasonCode":"add-wss","reasonDescription":" Izmaiņas veicamo darbu (tai skaitā, materiālu kategorijas) pozīcijās attiecībā pret noslēgtā Līguma (sākotnējo) tāmi","description":"Ņemot vērā radušās izmaiņas veicamo darbu (tai skaitā, materiālu kategorijas) pozīcijās attiecībā pret noslēgtā Līguma (sākotnējo) tāmi, palielināta Līguma summu par 8 922,11 EUR bez PVN, nosakot kopējo Līguma summu 443 353,69 EUR bez PVN, un attiecīgi veikti grozījumi Līguma Pielikumā Nr.1. Labots paziņojumā neprecīzi norādītais līguma izpildes termiņš.","value":443353.69,"winnerName":"Sabiedrība ar ierobežotu atbildību \"TELMS\"","sourceUrl":null,"date":null,"name":"Vidsprieguma līniju izbūve un pārbūve Ādažu, Tukuma un Ķekavas novados (5 daļas: IO-228133, IO-228168, IO-211726, IO-217890, IO-229578)"},{"procedureId":"1149e3a2-e2a7-4a63-bb75-16cc683fb2ab","buyerId":"40003857687","buyerName":"AS \"Sadales tīkls\"","cpv":"45231400-9","reasonCode":"add-wss","reasonDescription":"Izpildīto Būvdarbu (tai skaitā, izmantoto materiālu) apjoma izmaiņas","description":"Ievērojot faktiski izpildīto Būvdarbu (tai skaitā, izmantoto materiālu) apjomu, samazināta Līguma summa par 7 304,26 EUR bez PVN, un grozīts Līguma 3.3.punkts, izsakot to šādā redakcijā: \"3.3. Samaksa par šī Līguma 1.1.punktā un 1.2.punktā minētajiem darbiem kopā tiek noteikta 440 379,98 EUR (četri simti četrdesmit tūkstoši trīs simti septiņdesmit deviņi eiro un 98 centi) (turpmāk tekstā – \"Līguma","value":440379.98,"winnerName":"Sabiedrība ar ierobežotu atbildību \"AAO Projekts\"","sourceUrl":null,"date":null,"name":"Vidsprieguma Gaisvadu līniju automatizācija AUSTRUMU NODAĻĀ (9 daļas, 110 objekti)"},{"procedureId":"2f262ee5-664c-46e0-9c7a-ddc018a8258e","buyerId":"40003857687","buyerName":"AS \"Sadales tīkls\"","cpv":"45000000-7","reasonCode":"add-wss","reasonDescription":"Objekta īstenošanai nepieciešami papildu darbi un apjomi, kas nebija iekļauti sākotnējā tāmē","description":"Ievērojot SPSIL 66. panta trešās daļas 2. punktu un 66. panta ceturto daļu, veikti grozījumi līguma tāmē, pievienojot papildu darbus un palielinot apjomus par kopējo summu 4 321.39 EUR bez PVN. Papildu darbi ietver, bet ne tikai: 1) esošā bruģakmens seguma demontāžas un grunts atrakšanas laikā konstatēto 5 atsevišķu betona plākšņu demontāžu; 2) kāpņu pamatnē starp smilts pabērumu ievietoto dažādu ","value":425121.39,"winnerName":"SIA \"EKERS\"","sourceUrl":null,"date":null,"name":"Fasāžu un jumtu atjaunošana AS \"Sadales tīkls\" ēkām Valmierā, Limbažos, Bauskā, Jelgavā un Liepājā"},{"procedureId":"6b1723b2-d243-46d7-b768-e3a3c3bd56dd","buyerId":"40003857687","buyerName":"Akciju sabiedrība \"Sadales tīkls\"","cpv":"45231400-9","reasonCode":"add-wss","reasonDescription":"Pieslēguma vietas maiņa paralēlā objekta izbūves dēļ","description":"Būvdarbu laikā tika konstatēts, ka paralēlā objekta izbūves dēļ mainījās pieslēguma vieta, kā rezultātā brīvgaisa komutācijas izbūve nebija nepieciešama, bet bija jāveic papildu savienojošo uzmavu montāža. Lai pabeigtu darbus, nepieciešami grozījumi būvdarbu līgumā, ietverot izslēgtus darbus, apjomu izmaiņas un papildu darbu pozīcijas, rezultātā samazinot līguma summu par 7 589,02 EUR bez PVN un g","value":314883.8,"winnerName":"SIA \"DELTA EM\"","sourceUrl":null,"date":null,"name":"Vidsprieguma līniju izbūve un pārbūve (7 daļas_IO-218290, IO-233673, IO-233672, IO-259557, IO252363, IO-258205, IO-259554)"},{"procedureId":"1da0fb7c-7b52-40a8-b2eb-a268cbd1c2f6","buyerId":"40003857687","buyerName":"Akciju sabiedrība \"Sadales tīkls\"","cpv":"45231400-9","reasonCode":"add-wss","reasonDescription":"Izmaiņas normatīvajos aktos un būvdarbu gaitā konstatētie apstākļi","description":"1) Pamatojoties uz izmaiņām normatīvajos aktos, līgumam pievienots pielikums ar kiberdrošības prasībām, līguma vispārīgo noteikumu 5.4. punkts precizēts, to izsakot šādi: \"5.4. Kiberdrošības prasības\", un vispārīgie noteikumi papildināti ar punktiem 15.22. un 15.23. 2) Būvdarbu izpildes gaitā konstatēta neatbilstība starp projekta specifikācijā un izpildes plānā norādīto beztranšejas izbūves apjom","value":239405.27,"winnerName":"Sabiedrība ar ierobežotu atbildību \"KVĒLE\"","sourceUrl":null,"date":null,"name":"Elektroenerģijas sadales sistēmas elektrotīkla attīstība (6 daļas: IO-259499, IO-259488, IO-252502, IO-259427, IO-258599, IO-258019)"},{"procedureId":"fd48a524-f509-42ff-9774-923b4566b273","buyerId":"40003857687","buyerName":"Akciju sabiedrība \"Sadales tīkls\"","cpv":"45231400-9","reasonCode":"add-wss","reasonDescription":" Līguma vispārīgo noteikumu 18.1. un 21.5.punkts, SPSIL 66.panta trešās daļas 2.punkts un 66.panta ceturtā daļa","description":"1) Līgumam pievienots pielikums ar kiberdrošības prasībām, līguma vispārīgo noteikumu 5.4. punkts precizēts, to nosakot: \"5.4. Kiberdrošības prasības\", un vispārīgie noteikumi papildināti ar punktiem 15.22. un 15.23. 2) Ievērojot faktiski izpildīto būvdarbu (tai skaitā, izmantoto materiālu) apjomu, samazināta līguma summu par 277,68 EUR bez PVN, un grozīts līguma speciālo noteikumu 3.1.punkts, sam","value":96679.31,"winnerName":"Sabiedrība ar ierobežotu atbildību \"VSD serviss\"","sourceUrl":null,"date":null,"name":"Elektroenerģijas sadales sistēmas elektrotīkla attīstība (8 daļas: IO-256824, IO-255629, IO-257961, IO-250424, IO258174, IO-259049, IO-254684, IO-253198)"},{"procedureId":"fca9845c-f6f8-46df-b7ef-bc598da6ce94","buyerId":"40003857687","buyerName":"Akciju sabiedrība \"Sadales tīkls\"","cpv":"45231400-9","reasonCode":"add-wss","reasonDescription":"Neatbilstošas slēgiekārtas piegāde un būvdarbu apjoma precizēšana","description":"Būvdarbu laikā konstatēts, ka piegādāta neatbilstoša slēgiekārta, un nepieciešama jaunas slēgiekārtas atkārtota uzstādīšana un pieslēgšana, kā arī precizēti būvdarbu apjomi. Grozījumi ietver izslēgtus darbus no tāmes, izmaiņas darbu apjomos (palielinājums/samazinājums) un papildu darbu pozīcijas, tostarp materiālu kategorijas, kas iepriekš nebija iekļautas līguma tāmē. Līguma summa palielināta par","value":93759.38,"winnerName":"Sabiedrība ar ierobežotu atbildību \"WOLTEC\"","sourceUrl":null,"date":null,"name":"Tīkla digitālās vadības pilnveide un elektroenerģijas sadales sistēmas elektrotīkla attīstība (6 daļas: IO-259181, IO-273108, IO-273853, IO-273111, IO-263021, IO-273648)"},{"procedureId":"5998790d-85f0-4fe0-9966-05b58bb83915","buyerId":"40003857687","buyerName":"AS \"Sadales tīkls\"","cpv":"45231400-9","reasonCode":"add-wss","reasonDescription":"Objekta īstenošanai nepieciešami papildu darbi un apjomi, kas nebija iekļauti sākotnējā tāmē","description":"Ņemot vērā izstrādāto būvprojekta darbu izpildes tāmi, ir konstatētas izmaiņas veicamo darbu pozīcijās attiecībā pret noslēgtā Līguma (sākotnējo) tāmi. Izmaiņas ietver izslēgtus darbus, izmaiņas darbu apjomos (samazinājums/palielinājums) un papildu darbu pozīcijas, tai skaitā, materiālu kategorijas, kuras iepriekš nebija ietvertas Līguma izpildes darbu tāmē. Kopējā Līguma summa par būvprojektēšanu","value":91525.34,"winnerName":"Sabiedrība ar ierobežotu atbildību \"CVS\"","sourceUrl":null,"date":null,"name":"Vidsprieguma Gaisvadu līniju automatizācija RIETUMU NODAĻĀ (9 daļas, 83 objekti)"},{"procedureId":"5953173e-064f-49af-9271-4ebe7c8d9cfc","buyerId":"40003857687","buyerName":"AS \"Sadales tīkls\"","cpv":"45231400-9","reasonCode":"add-wss","reasonDescription":"Faktiski izpildīto Būvdarbu (tai skaitā, izmantoto materiālu) apjomu izmaiņas attiecībā pret noslēgtā Līguma (sākotnējo) tāmi.","description":"Ievērojot SPSIL 66. panta trešās daļas 2. punktu un 66. panta ceturto un piekto daļu, veikti grozījumi līguma tāmē, pievienojot papildus darbus un izslēdzot atsevišķus darbus, rezultātā samazinot kopējo summu par 261,56 EUR bez PVN un nosakot kopējo līguma summu 83 019,63 EUR bez PVN. Izslēgtie darbi ietver tādus darbus, kā par 37 metriem mazāk inastalēts VS kabelis, 46 metriem aizsargprofils, 6 m","value":83019.63,"winnerName":"Sabiedrība ar ierobežotu atbildību \"KVĒLE\"","sourceUrl":null,"date":null,"name":"Vidsprieguma līniju izbūve un pārbūve Jēkabpils, Salaspils un Tukuma novados (IO-252362, IO-257520, IO-258590)"},{"procedureId":"97215d35-21a6-4588-8e72-a6cde8a7f7e0","buyerId":"40003857687","buyerName":"Akciju sabiedrība \"Sadales tīkls\"","cpv":"45231400-9","reasonCode":"add-wss","reasonDescription":"Līguma vispārīgo noteikumu 18.1., 21.5.punkts, SPSIL 66.panta trešās daļas 2.punkts, 66.panta ceturtā daļa","description":"1) Līgumam pievienots pielikums ar kiberdrošības prasībām, līguma vispārīgo noteikumu 5.4. punkts precizēts, to nosakot: \"5.4. Kiberdrošības prasības\", un vispārīgie noteikumi papildināti ar punktiem 15.22. un 15.23. 2) Palielināta līguma summa par 4 810,63 EUR bez PVN, un grozīts līguma speciālo noteikumu 3.1.punkts, samaksu par veiktajiem būvdarbiem nosakot 79 900,15 EUR bez PVN. Precizēts līgum","value":79900.15,"winnerName":"Sabiedrība ar ierobežotu atbildību \"ELEKTRO VGI SIA\"","sourceUrl":null,"date":null,"name":"Tīkla digitālās vadības pilnveide un elektroenerģijas sadales sistēmas elektrotīkla attīstība (5 daļas: IO-259426, IO-273831, IO-272871, IO-273616, IO-250442)"},{"procedureId":"3db08ce3-3a40-40ec-8c66-44d977b79ab9","buyerId":"40003857687","buyerName":"AS \"Sadales tīkls\"","cpv":"45231400-9","reasonCode":"add-wss","reasonDescription":"Faktiski izpildīto Būvdarbu (tai skaitā, izmantoto materiālu) apjomu izmaiņas","description":"Ievērojot faktiski izpildīto Būvdarbu (tai skaitā, izmantoto materiālu) apjomu, Puses vienojas samazināt Līguma summu par 696,44 EUR bez PVN un grozīt Līguma 3.1.punktu.","value":76264.02,"winnerName":"SIA \"J.E.F.\"","sourceUrl":null,"date":null,"name":"Vidsprieguma līniju izbūve un pārbūve Olaines, Jelgavas, Ogres, Salaspils un Ādažu novados (IO-273852, IO-273825, IO-273830, IO-252357, IO-253005, IO-258069)"},{"procedureId":"95c2e342-a3f3-444a-80e9-770f0368ef53","buyerId":"40003857687","buyerName":"AS \"Sadales tīkls\"","cpv":"45231400-9","reasonCode":"add-wss","reasonDescription":"Objekta īstenošanai nepieciešami papildu darbi, kas nebija iekļauti sākotnējā tāmē","description":"Ievērojot SPSIL 66. panta trešās daļas 2. punktu un 66. panta ceturto daļu, veikti grozījumi līguma tāmē, pievienojot papildus darbus, rezultātā palielinot kopējo summu par 525,75 EUR bez PVN un nosakot kopējo līguma summu konkrētajam objektam 72 525,33 EUR bez PVN. Grozījumi ietver arī atsevišķu sākotnēji plānoto darbu izslēgšanu. Labots paziņojumā sākotnēji nepareizi norādītais līguma izpildes t","value":72525.33,"winnerName":"SIA \"REMUS ELEKTRO\"","sourceUrl":null,"date":null,"name":"Vidsprieguma līniju izbūve un pārbūve Rīgā, Talsos, Salaspilī, Olaines, Ķekavas, Ropažu un Ādažu novados (13 daļas)"},{"procedureId":"c6b0857a-9b09-440f-86d3-70ba5c024305","buyerId":"40003857687","buyerName":"Akciju sabiedrība \"Sadales tīkls\"","cpv":"45231400-9","reasonCode":"add-wss","reasonDescription":"Izmaiņas normatīvajos aktos par kiberdrošības prasībām un būvdarbu apjomu precizēšana","description":"1) Pamatojoties uz izmaiņām normatīvajos aktos, līgumam pievienots pielikums ar kiberdrošības prasībām, līguma vispārīgo noteikumu 5.4. punkts precizēts, to izsakot: \"5.4. Kiberdrošības prasības\", un vispārīgie noteikumi papildināti ar punktiem 15.22. un 15.23. 2) Konstatēts, ka būvprojektā plānotie būvdarbu apjomi neatbilst faktiskajai situācijai dabai, tādēļ nepieciešami papildus demontāžas darb","value":58975.17,"winnerName":"Sabiedrība ar ierobežotu atbildību \"EnergoUP\"","sourceUrl":null,"date":null,"name":"Elektroenerģijas sadales sistēmas elektrotīkla attīstība (8 daļas: IO-254733, IO-245283, IO-259389, IO-259344, IO-258901, IO-259560, IO-259371, IO-259553)"},{"procedureId":"c60e813a-9e78-482c-ad29-4a7d0331d745","buyerId":"40003857687","buyerName":"AS \"Sadales tīkls\"","cpv":"45231400-9","reasonCode":"add-wss","reasonDescription":"Objekta īstenošanai nepieciešami papildu darbi, kas nebija iekļauti sākotnējā tāmē","description":"Ievērojot SPSIL 66. panta trešās daļas 2. punktu un 66. panta ceturto un piekto daļu, veikti grozījumi līguma tāmē, pievienojot papildus darbus un izslēdzot atsevišķus darbus, rezultātā samazinot kopējo summu par 66,78 EUR bez PVN un nosakot kopējo līguma summu 57 918,64 EUR bez PVN.","value":57918.64,"winnerName":"SIA \"J.E.F.\"","sourceUrl":null,"date":null,"name":"Vidsprieguma līniju izbūve un pārbūve (8 daļas: IO-259489, IO-259388, IO-257804, IO-252390, IO-258968, IO-258710, IO-257893, IO-272886)"},{"procedureId":"b2e61183-fce0-4b12-85bf-9cb9815a2a90","buyerId":"40003857687","buyerName":"AS \"Sadales tīkls\"","cpv":"45231400-9","reasonCode":"add-wss","reasonDescription":"Objekta īstenošanai nepieciešami papildu darbi un apjomi, kas nebija iekļauti sākotnējā tāmē","description":"Ievērojot SPSIL 66.panta trešās daļas 2.punktu un 66.panta ceturto un piekto daļu, veiktas izmaiņas tāmē - pievienoti papildu darbi par kopējo summu 38,72 EUR bez PVN. Grozījumi ietver arī atsevišķu sākotnēji plānoto darbu izslēgšanu kopējo summu 89,50 EUR bez PVN","value":49681.68,"winnerName":"Sabiedrība ar ierobežotu atbildību \"WOLTEC\"","sourceUrl":null,"date":null,"name":"Vidsprieguma līniju izbūve un pārbūve (8 daļas: IO257004, IO-258606, IO-258052, IO-273667, IO259289, IO-259558, IO-257864, IO-259556)"},{"procedureId":"36083efe-a75d-4ef4-b27b-afbfdbc4e3ed","buyerId":"40003857687","buyerName":"Akciju sabiedrība \"Sadales tīkls\"","cpv":"45231400-9","reasonCode":"add-wss","reasonDescription":"Izmaiņas normatīvajos aktos par kiberdrošības prasībām un ","description":"1) Pamatojoties uz izmaiņām normatīvajos aktos, līgumam pievienots pielikums ar kiberdrošības prasībām, līguma vispārīgo noteikumu 5.4. punkts precizēts, to nosakot: \"5.4. Kiberdrošības prasības\", un vispārīgie noteikumi papildināti ar punktiem 15.22. un 15.23. 2) Būvprojekta specifikācijā norādītais kabeļu ieguldīšanas apjoms tranšejā ir mazāks nekā dabā nepieciešams, tādēļ jāveic papildu kabeļa ","value":38219.79,"winnerName":"Sabiedrība ar ierobežotu atbildību \"KVĒLE\"","sourceUrl":null,"date":null,"name":"Elektroenerģijas sadales sistēmas elektrotīkla attīstība (5 daļas: IO-258128, IO-258602, IO-259045, IO-258175, IO-259500)"},{"procedureId":"9303c7f6-b196-4357-bde7-d00bbe270cb0","buyerId":"40003857687","buyerName":"Akciju sabiedrība \"Sadales tīkls\"","cpv":"45231400-9","reasonCode":"add-wss","reasonDescription":"Izmaiņas normatīvajos aktos un būvprojektā norādīto darbu un materiālu apjomu neatbilstība faktiskajām būvdarbu vajadzībām","description":"1) Līgumam pievienots pielikums ar kiberdrošības prasībām, līguma vispārīgo noteikumu 5.4. punkts precizēts, to izsakot šādā redakcijā: \"5.4. Kiberdrošības prasības\", un vispārīgie noteikumi papildināti ar punktiem 15.22. un 15.23. 2) Palielināta līguma summa par 218,65 EUR bez PVN, un grozīts līguma speciālo noteikumu 3.1. punkts, samaksu par veiktajiem būvdarbiem nosakot 36 471,53 EUR bez PVN. ","value":36471.53,"winnerName":"Sabiedrība ar ierobežotu atbildību \"MARITEC\"","sourceUrl":null,"date":null,"name":"Elektroenerģijas sadales sistēmas elektrotīkla attīstība (6 daļas: IO-259485, IO-250404, IO-252387, IO-258017, IO-250262, IO-257003)"},{"procedureId":"bfe46a5b-69d2-443b-af9e-ca9815fabbc0","buyerId":"40003857687","buyerName":"AS \"Sadales tīkls\"","cpv":"45231400-9","reasonCode":"add-wss","reasonDescription":"Būvprojektā elektropārvades kabeļu līnijas apjomi ir norādīti mazāki nekā nepieciešams realizēt objektā","description":"Būvprojektā elektropārvades kabeļu līnijas apjomi norādīti mazāki nekā nepieciešams faktiski objekta izbūvei, tāpēc veikti grozījumi līguma pielikumā Nr.1.","value":35028.94,"winnerName":"SIA \"DELTA EM\"","sourceUrl":null,"date":null,"name":"Tīkla digitālās vadības pilnveide un elektroenerģijas sadales sistēmas elektrotīkla attīstība (7 daļas: IO-261730, IO-272891, IO-258897, IO-257000, IO-258116, IO-259367, IO-258605)"},{"procedureId":"72b6a466-9513-40de-a4ba-b52ae0939945","buyerId":"40003857687","buyerName":"AS \"Sadales tīkls\"","cpv":"45231400-9","reasonCode":"add-wss","reasonDescription":"Objekta īstenošanai nepieciešamas izmaiņas veicamo darbu pozīcijās attiecībā pret noslēgtā Līguma (sākotnējo) tāmi","description":"Saskaņā ar Līguma nosacījumiem un atbilstoši izsniegtajam projektēšanas uzdevumam, Darbuzņēmējs veica būvprojekta izstrādi, kas ietver topogrāfisko uzmērīšanu, saskaņojumu saņemšanu no ietekmēto zemju īpašniekiem, inženiertīklu turētājiem un būvvaldes. Ņemot vērā izstrādātā būvprojekta darbu izpildes tāmi, ir konstatējamas izmaiņas veicamo darbu pozīcijās attiecībā pret noslēgtā Līguma (sākotnējo)","value":29558.1,"winnerName":"Sabiedrība ar ierobežotu atbildību \"WOLTEC\"","sourceUrl":null,"date":null,"name":"Vidsprieguma Gaisvadu līniju automatizācija VIDZEMES NODAĻĀ (10 daļas, 70 objekti)"},{"procedureId":"98435efa-fed4-4604-bd2b-147deaca289d","buyerId":"40003857687","buyerName":"AS \"Sadales tīkls\"","cpv":"45231400-9","reasonCode":"add-wss","reasonDescription":"Objekta tehniskā risinājuma izmaiņas","description":"Sakarā ar tehniskā risinājuma izmaiņām ir precizēts veicamo būvdarbu apjoms — nepieciešama tranšejas (bedres) izbūve ZS uzmavām un ZS izolācijas kabeļa savienošanas uzmavas montāža, līdz ar to Līguma summa tiek palielināta par 498,29 EUR (bez PVN), un jaunā kopējā Līguma summa ir 22 407,34 EUR (bez PVN). Attiecīgi tiek grozīts arī Līguma 3.1. punkts.","value":22407.34,"winnerName":"SIA \"TALSU SPRIEGUMS\"","sourceUrl":null,"date":null,"name":"Elektrisko transportlīdzekļu uzlādes pieslēgumu izbūve (4.apjoms)"},{"procedureId":"f6c2ea2d-10a6-412d-99c7-44ae511fa7a2","buyerId":"40003857687","buyerName":"AS \"Sadales tīkls\"","cpv":"45231400-9","reasonCode":"add-wss","reasonDescription":"Izmaiņas veicamo darbu (tai skaitā, materiālu kategorijas) pozīcijās attiecībā pret noslēgtā Līguma (sākotnējo) tāmi un AS \"Sadales tīkls\" personāla maiņa ","description":"1. Ņemot vērā, ka radušās izmaiņas veicamo darbu (tai skaitā, materiālu kategorijas) pozīcijās attiecībā pret noslēgtā Līguma (sākotnējo) tāmi, Līdzēji vienojas palielināt Līguma summu par 985,91 EUR bez PVN, nosakot kopējo Līguma summu 23 034,57 EUR bez PVN, un veicot grozījumus Līguma 1. un 2.pielikumā, izsakot tos jaunā redakcijā.\n\n2. Sakarā ar AS \"Sadales tīkls\" personāla maiņu, Līdzēji vienoj","value":22048.66,"winnerName":"Sabiedrība ar ierobežotu atbildību \"AAO Projekts\"","sourceUrl":null,"date":null,"name":"Elektrisko transportlīdzekļu pieslēgumu projektēšana un izbūve"},{"procedureId":"90325b7d-a00e-46a7-8016-c32ee258a39b","buyerId":"40003857687","buyerName":"AS \"Sadales tīkls\"","cpv":"45231400-9","reasonCode":"add-wss","reasonDescription":"Objekta īstenošanai nepieciešami papildu darbi un apjomi, kas nebija iekļauti sākotnējā tāmē","description":"Ievērojot SPSIL 66. panta trešās daļas 2. punktu un 66. panta ceturto daļu, veikti grozījumi līguma tāmē, pievienojot papildus darbus (t.sk. ar tiem saistītos materiālus) un apjomus un izslēdzot attiecīgus darbus un apjomus, rezultātā samazinot kopējo summu par 594.00 EUR bez PVN, nosakot kopējo līguma summu 21 018,10 EUR bez PVN un veicot grozījumus Līguma Pielikumā Nr.1, izsakot to jaunā redakci","value":21018.1,"winnerName":"SIA \"Universālais Energoceltnieks\"","sourceUrl":null,"date":null,"name":"Elektrisko transportlīdzekļu pieslēgumu projektēšana un izbūve Nr.3 (ANM ietvaros)"}]}},"flaggedLots":[{"indicator":"B1","scope":"lot","buyerId":"40003857687","status":"RiskFound","level":"yellow","score":null,"lotId":"268547","detail":{"receivedBids":1,"sourceUrl":"https://www.eis.gov.lv/EKEIS/Supplier/Procurement/110451"}},{"indicator":"B1","scope":"lot","buyerId":"40003857687","status":"RiskFound","level":"yellow","score":null,"lotId":"268548","detail":{"receivedBids":1,"sourceUrl":"https://www.eis.gov.lv/EKEIS/Supplier/Procurement/110451"}},{"indicator":"B1","scope":"lot","buyerId":"40003857687","status":"RiskFound","level":"yellow","score":null,"lotId":"385564","detail":{"receivedBids":1,"sourceUrl":"https://www.eis.gov.lv/EKEIS/Supplier/Procurement/122892"}},{"indicator":"B1","scope":"lot","buyerId":"40003857687","status":"RiskFound","level":"yellow","score":null,"lotId":"388144","detail":{"receivedBids":1,"sourceUrl":"https://www.eis.gov.lv/EKEIS/Supplier/Procurement/118710"}},{"indicator":"B1","scope":"lot","buyerId":"40003857687","status":"RiskFound","level":"yellow","score":null,"lotId":"388145","detail":{"receivedBids":1,"sourceUrl":"https://www.eis.gov.lv/EKEIS/Supplier/Procurement/118710"}},{"indicator":"B1","scope":"lot","buyerId":"40003857687","status":"RiskFound","level":"yellow","score":null,"lotId":"388147","detail":{"receivedBids":1,"sourceUrl":"https://www.eis.gov.lv/EKEIS/Supplier/Procurement/118710"}},{"indicator":"B1","scope":"lot","buyerId":"40003857687","status":"RiskFound","level":"yellow","score":null,"lotId":"388148","detail":{"receivedBids":1,"sourceUrl":"https://www.eis.gov.lv/EKEIS/Supplier/Procurement/118710"}},{"indicator":"B1","scope":"lot","buyerId":"40003857687","status":"RiskFound","level":"yellow","score":null,"lotId":"388149","detail":{"receivedBids":1,"sourceUrl":"https://www.eis.gov.lv/EKEIS/Supplier/Procurement/118710"}},{"indicator":"B1","scope":"lot","buyerId":"40003857687","status":"RiskFound","level":"yellow","score":null,"lotId":"398415","detail":{"receivedBids":1,"sourceUrl":"https://www.eis.gov.lv/EKEIS/Supplier/Procurement/113877"}},{"indicator":"B1","scope":"lot","buyerId":"40003857687","status":"RiskFound","level":"yellow","score":null,"lotId":"398428","detail":{"receivedBids":1,"sourceUrl":"https://www.eis.gov.lv/EKEIS/Supplier/Procurement/113877"}},{"indicator":"B1","scope":"lot","buyerId":"40003857687","status":"RiskFound","level":"yellow","score":null,"lotId":"398429","detail":{"receivedBids":1,"sourceUrl":"https://www.eis.gov.lv/EKEIS/Supplier/Procurement/113877"}},{"indicator":"B1","scope":"lot","buyerId":"40003857687","status":"RiskFound","level":"yellow","score":null,"lotId":"398430","detail":{"receivedBids":1,"sourceUrl":"https://www.eis.gov.lv/EKEIS/Supplier/Procurement/113877"}},{"indicator":"B1","scope":"lot","buyerId":"40003857687","status":"RiskFound","level":"yellow","score":null,"lotId":"398432","detail":{"receivedBids":1,"sourceUrl":"https://www.eis.gov.lv/EKEIS/Supplier/Procurement/113877"}},{"indicator":"B1","scope":"lot","buyerId":"40003857687","status":"RiskFound","level":"yellow","score":null,"lotId":"398433","detail":{"receivedBids":1,"sourceUrl":"https://www.eis.gov.lv/EKEIS/Supplier/Procurement/113877"}},{"indicator":"B1","scope":"lot","buyerId":"40003857687","status":"RiskFound","level":"yellow","score":null,"lotId":"398434","detail":{"receivedBids":1,"sourceUrl":"https://www.eis.gov.lv/EKEIS/Supplier/Procurement/113877"}},{"indicator":"B1","scope":"lot","buyerId":"40003857687","status":"RiskFound","level":"yellow","score":null,"lotId":"398435","detail":{"receivedBids":1,"sourceUrl":"https://www.eis.gov.lv/EKEIS/Supplier/Procurement/113877"}},{"indicator":"B1","scope":"lot","buyerId":"40003857687","status":"RiskFound","level":"yellow","score":null,"lotId":"398438","detail":{"receivedBids":1,"sourceUrl":"https://www.eis.gov.lv/EKEIS/Supplier/Procurement/113877"}},{"indicator":"B1","scope":"lot","buyerId":"40003857687","status":"RiskFound","level":"yellow","score":null,"lotId":"398444","detail":{"receivedBids":1,"sourceUrl":"https://www.eis.gov.lv/EKEIS/Supplier/Procurement/113877"}},{"indicator":"B1","scope":"lot","buyerId":"40003857687","status":"RiskFound","level":"yellow","score":null,"lotId":"398445","detail":{"receivedBids":1,"sourceUrl":"https://www.eis.gov.lv/EKEIS/Supplier/Procurement/113877"}},{"indicator":"B1","scope":"lot","buyerId":"40003857687","status":"RiskFound","level":"yellow","score":null,"lotId":"398447","detail":{"receivedBids":1,"sourceUrl":"https://www.eis.gov.lv/EKEIS/Supplier/Procurement/113877"}},{"indicator":"B1","scope":"lot","buyerId":"40003857687","status":"RiskFound","level":"yellow","score":null,"lotId":"398451","detail":{"receivedBids":1,"sourceUrl":"https://www.eis.gov.lv/EKEIS/Supplier/Procurement/113877"}},{"indicator":"B1","scope":"lot","buyerId":"40003857687","status":"RiskFound","level":"yellow","score":null,"lotId":"398452","detail":{"receivedBids":1,"sourceUrl":"https://www.eis.gov.lv/EKEIS/Supplier/Procurement/113877"}},{"indicator":"B1","scope":"lot","buyerId":"40003857687","status":"RiskFound","level":"yellow","score":null,"lotId":"398453","detail":{"receivedBids":1,"sourceUrl":"https://www.eis.gov.lv/EKEIS/Supplier/Procurement/113877"}},{"indicator":"B1","scope":"lot","buyerId":"40003857687","status":"RiskFound","level":"yellow","score":null,"lotId":"398456","detail":{"receivedBids":1,"sourceUrl":"https://www.eis.gov.lv/EKEIS/Supplier/Procurement/113877"}},{"indicator":"B1","scope":"lot","buyerId":"40003857687","status":"RiskFound","level":"yellow","score":null,"lotId":"398457","detail":{"receivedBids":1,"sourceUrl":"https://www.eis.gov.lv/EKEIS/Supplier/Procurement/113877"}},{"indicator":"B1","scope":"lot","buyerId":"40003857687","status":"RiskFound","level":"yellow","score":null,"lotId":"398458","detail":{"receivedBids":1,"sourceUrl":"https://www.eis.gov.lv/EKEIS/Supplier/Procurement/113877"}},{"indicator":"B1","scope":"lot","buyerId":"40003857687","status":"RiskFound","level":"yellow","score":null,"lotId":"398460","detail":{"receivedBids":1,"sourceUrl":"https://www.eis.gov.lv/EKEIS/Supplier/Procurement/113877"}},{"indicator":"B1","scope":"lot","buyerId":"40003857687","status":"RiskFound","level":"yellow","score":null,"lotId":"398461","detail":{"receivedBids":1,"sourceUrl":"https://www.eis.gov.lv/EKEIS/Supplier/Procurement/113877"}},{"indicator":"B1","scope":"lot","buyerId":"40003857687","status":"RiskFound","level":"yellow","score":null,"lotId":"398462","detail":{"receivedBids":1,"sourceUrl":"https://www.eis.gov.lv/EKEIS/Supplier/Procurement/113877"}},{"indicator":"B1","scope":"lot","buyerId":"40003857687","status":"RiskFound","level":"yellow","score":null,"lotId":"398464","detail":{"receivedBids":1,"sourceUrl":"https://www.eis.gov.lv/EKEIS/Supplier/Procurement/113877"}},{"indicator":"B1","scope":"lot","buyerId":"40003857687","status":"RiskFound","level":"yellow","score":null,"lotId":"398468","detail":{"receivedBids":1,"sourceUrl":"https://www.eis.gov.lv/EKEIS/Supplier/Procurement/113877"}},{"indicator":"B1","scope":"lot","buyerId":"40003857687","status":"RiskFound","level":"yellow","score":null,"lotId":"398821","detail":{"receivedBids":1,"sourceUrl":null}},{"indicator":"B1","scope":"lot","buyerId":"40003857687","status":"RiskFound","level":"yellow","score":null,"lotId":"399001","detail":{"receivedBids":1,"sourceUrl":null}},{"indicator":"B1","scope":"lot","buyerId":"40003857687","status":"RiskFound","level":"yellow","score":null,"lotId":"398683","detail":{"receivedBids":1,"sourceUrl":"https://www.eis.gov.lv/EKEIS/Supplier/Procurement/118762"}},{"indicator":"B1","scope":"lot","buyerId":"40003857687","status":"RiskFound","level":"yellow","score":null,"lotId":"398684","detail":{"receivedBids":1,"sourceUrl":"https://www.eis.gov.lv/EKEIS/Supplier/Procurement/118762"}},{"indicator":"B1","scope":"lot","buyerId":"40003857687","status":"RiskFound","level":"yellow","score":null,"lotId":"398687","detail":{"receivedBids":1,"sourceUrl":"https://www.eis.gov.lv/EKEIS/Supplier/Procurement/118762"}},{"indicator":"B1","scope":"lot","buyerId":"40003857687","status":"RiskFound","level":"yellow","score":null,"lotId":"398688","detail":{"receivedBids":1,"sourceUrl":"https://www.eis.gov.lv/EKEIS/Supplier/Procurement/118762"}},{"indicator":"B1","scope":"lot","buyerId":"40003857687","status":"RiskFound","level":"yellow","score":null,"lotId":"398689","detail":{"receivedBids":1,"sourceUrl":"https://www.eis.gov.lv/EKEIS/Supplier/Procurement/118762"}},{"indicator":"B1","scope":"lot","buyerId":"40003857687","status":"RiskFound","level":"yellow","score":null,"lotId":"398691","detail":{"receivedBids":1,"sourceUrl":"https://www.eis.gov.lv/EKEIS/Supplier/Procurement/118762"}},{"indicator":"B1","scope":"lot","buyerId":"40003857687","status":"RiskFound","level":"yellow","score":null,"lotId":"398692","detail":{"receivedBids":1,"sourceUrl":"https://www.eis.gov.lv/EKEIS/Supplier/Procurement/118762"}},{"indicator":"B1","scope":"lot","buyerId":"40003857687","status":"RiskFound","level":"yellow","score":null,"lotId":"398694","detail":{"receivedBids":1,"sourceUrl":"https://www.eis.gov.lv/EKEIS/Supplier/Procurement/118762"}},{"indicator":"B1","scope":"lot","buyerId":"40003857687","status":"RiskFound","level":"yellow","score":null,"lotId":"398695","detail":{"receivedBids":1,"sourceUrl":"https://www.eis.gov.lv/EKEIS/Supplier/Procurement/118762"}},{"indicator":"B1","scope":"lot","buyerId":"40003857687","status":"RiskFound","level":"yellow","score":null,"lotId":"398698","detail":{"receivedBids":1,"sourceUrl":"https://www.eis.gov.lv/EKEIS/Supplier/Procurement/118762"}},{"indicator":"B1","scope":"lot","buyerId":"40003857687","status":"RiskFound","level":"yellow","score":null,"lotId":"398699","detail":{"receivedBids":1,"sourceUrl":"https://www.eis.gov.lv/EKEIS/Supplier/Procurement/118762"}},{"indicator":"B1","scope":"lot","buyerId":"40003857687","status":"RiskFound","level":"yellow","score":null,"lotId":"398704","detail":{"receivedBids":1,"sourceUrl":"https://www.eis.gov.lv/EKEIS/Supplier/Procurement/118762"}},{"indicator":"B1","scope":"lot","buyerId":"40003857687","status":"RiskFound","level":"yellow","score":null,"lotId":"398710","detail":{"receivedBids":1,"sourceUrl":"https://www.eis.gov.lv/EKEIS/Supplier/Procurement/118762"}},{"indicator":"B1","scope":"lot","buyerId":"40003857687","status":"RiskFound","level":"yellow","score":null,"lotId":"398711","detail":{"receivedBids":1,"sourceUrl":"https://www.eis.gov.lv/EKEIS/Supplier/Procurement/118762"}},{"indicator":"B1","scope":"lot","buyerId":"40003857687","status":"RiskFound","level":"yellow","score":null,"lotId":"398712","detail":{"receivedBids":1,"sourceUrl":"https://www.eis.gov.lv/EKEIS/Supplier/Procurement/118762"}},{"indicator":"B1","scope":"lot","buyerId":"40003857687","status":"RiskFound","level":"yellow","score":null,"lotId":"401884","detail":{"receivedBids":1,"sourceUrl":"https://www.eis.gov.lv/EKEIS/Supplier/Procurement/114084"}},{"indicator":"B1","scope":"lot","buyerId":"40003857687","status":"RiskFound","level":"yellow","score":null,"lotId":"417143","detail":{"receivedBids":1,"sourceUrl":"https://www.eis.gov.lv/EKEIS/Supplier/Procurement/129816"}}],"topSuppliers":[{"winnerId":"40003511655","fileId":"40003511655","name":"SIA \"Ditra Networks\"","value":35704069,"contracts":41,"singleBidRate":0.24},{"winnerId":"40003524433","fileId":"40003524433","name":"SIA \"DELTA EM\"","value":27787160,"contracts":57,"singleBidRate":0.04},{"winnerId":"43603002795","fileId":"43603002795","name":"Sabiedrība ar ierobežotu atbildību \"KVĒLE\"","value":24827136,"contracts":32,"singleBidRate":0.03},{"winnerId":"50003563201","fileId":"50003563201","name":"Sabiedrība ar ierobežotu atbildību \"Enersense\"","value":24350548,"contracts":38,"singleBidRate":0.05},{"winnerId":"44103097350","fileId":"44103097350","name":"Sabiedrība ar ierobežotu atbildību \"WOLTEC\"","value":22853294,"contracts":24,"singleBidRate":0.08},{"winnerId":"45403020866","fileId":"45403020866","name":"Sabiedrība ar ierobežotu atbildību \"Hanza-elektro\"","value":22768370,"contracts":20,"singleBidRate":0},{"winnerId":"40003490137","fileId":"40003490137","name":"Sabiedrība ar ierobežotu atbildību \"TELMS\"","value":21794106,"contracts":16,"singleBidRate":0.06},{"winnerId":"49003000127","fileId":"49003000127","name":"SIA \"TALSU SPRIEGUMS\"","value":21507492,"contracts":23,"singleBidRate":0},{"winnerId":"59503004211","fileId":"59503004211","name":"SIA \"FARADS\"","value":21068468,"contracts":14,"singleBidRate":0},{"winnerId":"48503004386","fileId":"48503004386","name":"SIA \"J.E.F.\"","value":20994353,"contracts":8,"singleBidRate":0},{"winnerId":"40003458871","fileId":"40003458871","name":"Sabiedrība ar ierobežotu atbildību \"ENERGOREMONTS RĪGA\"","value":20729926,"contracts":7,"singleBidRate":0.14},{"winnerId":"40003291535","fileId":"40003291535","name":"Alūksnes rajona sabiedrība ar ierobežotu atbildību firma \"ALŪKSNES ENERGOCELTNIEKS\"","value":20596547,"contracts":3,"singleBidRate":0}],"sharedOwnerGroups":[{"person":"Šimins Artūrs","winners":[{"fileId":"40003856361","name":"SIA \"Energokomplekss\"","value":9290089,"contracts":9,"role":"valde"},{"fileId":"40003012798","name":"Akciju sabiedrība ENERGOFIRMA \"JAUDA\"","value":2617266,"contracts":18,"role":"valde"}]},{"person":"Kristaps Bleija","winners":[{"fileId":"40003856361","name":"SIA \"Energokomplekss\"","value":9290089,"contracts":9,"role":"PLG"},{"fileId":"40203413785","name":"SIA Power Solution","value":0,"contracts":1,"role":"PLG"}]},{"person":"Jānis Bikiņš","winners":[{"fileId":"44103097350","name":"Sabiedrība ar ierobežotu atbildību \"WOLTEC\"","value":45118187,"contracts":71,"role":"valde"},{"fileId":"44103024338","name":"Sabiedrība ar ierobežotu atbildību \"MARITEC\"","value":531415,"contracts":9,"role":"PLG"}]},{"person":"Jānis Kols","winners":[{"fileId":"40003500721","name":"Sabiedrība ar ierobežotu atbildību \"Reck\"","value":30202165,"contracts":25,"role":"PLG"},{"fileId":"44103024338","name":"Sabiedrība ar ierobežotu atbildību \"MARITEC\"","value":531415,"contracts":9,"role":"PLG"}]},{"person":"Ainārs Kazušs","winners":[{"fileId":"45403020372","name":"Sabiedrība ar ierobežotu atbildību \"MVR LUX\"","value":1751134,"contracts":11,"role":"valde"},{"fileId":"40203008390","name":"Eco LUX Latvia SIA","value":206305,"contracts":3,"role":"PLG"}]},{"person":"Deniss Vrevskis","winners":[{"fileId":"40103386423","name":"Sabiedrība ar ierobežotu atbildību \"DEVRE LV\"","value":2025334,"contracts":8,"role":"PLG"},{"fileId":"44103125989","name":"SIA \"DEVRE\"","value":585085,"contracts":32,"role":"PLG"}]},{"person":"Valdis Rudzis","winners":[{"fileId":"40103191992","name":"Sabiedrība ar ierobežotu atbildību \"ECC LATVIJA\"","value":2371301,"contracts":15,"role":"PLG"},{"fileId":"40003002094","name":"Sabiedrība ar ierobežotu atbildību \"ELKO\"","value":1913507,"contracts":15,"role":"PLG"}]},{"person":"Tatjana Šimanska","winners":[{"fileId":"41502003093","name":"Sabiedrība ar ierobežotu atbildību \"SZMA\"","value":20572992,"contracts":1,"role":"PLG"},{"fileId":"41503011365","name":"Sabiedrība ar ierobežotu atbildību \"BALTIC ELEKTROMONTĀŽA\"","value":1390397,"contracts":14,"role":"PLG"}]}],"meta":{"coverage":"2023-10-25 … 2026-06-17","source":"IUB visa pieejamā vēsture","generatedAt":"2026-06-20T13:42:24.424Z","lots":67411,"buyers":916}}