{"buyerId":"44103022271","buyerName":"SIA „Valmieras Namsaimnieks”","riskScore":47,"combinedScore":14,"combinedLevel":"green","layerScores":{"A":0,"B":23,"C":47,"D":0,"E":0,"G":0},"result":{"indicator":"B1","scope":"buyer","buyerId":"44103022271","status":"RiskNotFound","level":null,"score":0,"detail":{"buyerName":"SIA „Valmieras Namsaimnieks”","winnerChosenLots":40,"singleBidLots":4,"nationalAvg":0.2484,"flaggedLotIds":["400431","379761","438437","452892"],"singleBidRate":0.1,"relativeRatio":0.403}},"b2":{"indicator":"B2","scope":"buyer","buyerId":"44103022271","status":"RiskNotFound","level":null,"score":23,"detail":{"buyerName":"SIA „Valmieras Namsaimnieks”","awardedLots":40,"basis":"value","distinctWinners":26,"hhi":0.213,"topWinnerShare":0.327,"topWinnerId":"42103088773","topWinnerName":"SIA \"Kvartāls\"","totalAwardValue":5569081.94}},"a":{"indicator":"A","scope":"buyer","buyerId":"44103022271","status":"RiskNotFound","level":null,"score":0,"detail":{"buyerName":"SIA „Valmieras Namsaimnieks”","usableLots":39,"clusterCount":0,"clusters":[]}},"c":{"indicator":"C","scope":"buyer","buyerId":"44103022271","status":"RiskFound","level":"yellow","score":47,"detail":{"buyerName":"SIA „Valmieras Namsaimnieks”","evaluatedLots":39,"maxZ":1.64,"priceFlags":[{"lotId":"445173","value":1821541.58,"cpv":"45000000-7","z":1.64,"obs":2680,"sourceUrl":"https://www.eis.gov.lv/EKEIS/Supplier/Procurement/133161"},{"lotId":"445095","value":924239.49,"cpv":"45000000-7","z":1.26,"obs":2680,"sourceUrl":"https://www.eis.gov.lv/EKEIS/Supplier/Procurement/126225"},{"lotId":"402342","value":809398.7,"cpv":"45000000-7","z":1.19,"obs":2680,"sourceUrl":"https://www.eis.gov.lv/EKEIS/Supplier/Procurement/123909"}]}},"e":{"indicator":"E","scope":"buyer","buyerId":"44103022271","status":"RiskNotFound","level":null,"score":0,"detail":{"buyerName":"SIA „Valmieras Namsaimnieks”","awardedLots":40,"nonCompetitiveLots":0,"nonCompetitiveShare":0,"flaggedLotIds":[]}},"d":{"indicator":"D","scope":"buyer","buyerId":"44103022271","status":"RiskNotFound","level":null,"score":0,"detail":{"buyerName":"SIA „Valmieras Namsaimnieks”","evaluableAwards":38,"newWinnerAwards":0,"veryNewAwards":0,"newWinners":[]}},"g":{"indicator":"G","scope":"buyer","buyerId":"44103022271","status":"RiskNotFound","level":null,"score":0,"detail":{"buyerName":"SIA „Valmieras Namsaimnieks”","contracts":40,"modifiedContracts":0,"substantiveContracts":0,"substantiveRate":0,"byReasonCode":{},"modifications":[]}},"flaggedLots":[{"indicator":"B1","scope":"lot","buyerId":"44103022271","status":"RiskFound","level":"yellow","score":null,"lotId":"400431","detail":{"receivedBids":1,"sourceUrl":"https://www.eis.gov.lv/EKEIS/Supplier/Procurement/133186"}},{"indicator":"B1","scope":"lot","buyerId":"44103022271","status":"RiskFound","level":"yellow","score":null,"lotId":"379761","detail":{"receivedBids":1,"sourceUrl":"https://www.eis.gov.lv/EKEIS/Supplier/Procurement/129392"}},{"indicator":"B1","scope":"lot","buyerId":"44103022271","status":"RiskFound","level":"yellow","score":null,"lotId":"438437","detail":{"receivedBids":1,"sourceUrl":"https://www.eis.gov.lv/EKEIS/Supplier/Procurement/148045"}},{"indicator":"B1","scope":"lot","buyerId":"44103022271","status":"RiskFound","level":"yellow","score":null,"lotId":"452892","detail":{"receivedBids":1,"sourceUrl":"https://www.eis.gov.lv/EKEIS/Supplier/Procurement/143854"}}],"topSuppliers":[{"winnerId":"42103088773","fileId":"42103088773","name":"SIA \"Kvartāls\"","value":1821542,"contracts":1,"singleBidRate":0},{"winnerId":"44103001903","fileId":"44103001903","name":"SIA \"EKERS\"","value":1281693,"contracts":3,"singleBidRate":0.33},{"winnerId":"44103043748","fileId":"44103043748","name":"Sabiedrība ar ierobežotu atbildību \"SANART\"","value":1242759,"contracts":2,"singleBidRate":0},{"winnerId":"40103867145","fileId":"40103867145","name":"AS \"VIADA Baltija\"","value":167896,"contracts":2,"singleBidRate":0},{"winnerId":"121543961","fileId":"121543961","name":"UAB \"Keluva\"","value":149830,"contracts":2,"singleBidRate":0},{"winnerId":"40003242737","fileId":"40003242737","name":"Akciju sabiedrība \"VIRŠI-A\"","value":120270,"contracts":1,"singleBidRate":0},{"winnerId":"40103840140","fileId":"40103840140","name":"AAS \"BTA Baltic Insurance Company\"","value":112614,"contracts":4,"singleBidRate":0},{"winnerId":"40103625065","fileId":"40103625065","name":"\"LAT SALT TRADE\" SIA","value":112000,"contracts":1,"singleBidRate":0},{"winnerId":"40003242722","fileId":"40003242722","name":"Sabiedrība ar ierobežotu atbildību \"NORDE\"","value":67361,"contracts":2,"singleBidRate":1},{"winnerId":"40003225811","fileId":"40003225811","name":"Sabiedrība ar ierobežotu atbildību \"KOMERCVEIKSMES\"","value":63400,"contracts":4,"singleBidRate":0},{"winnerId":"50003719281","fileId":"50003719281","name":"SIA \"DEPO DIY\"","value":62113,"contracts":2,"singleBidRate":0},{"winnerId":"44103087969","fileId":"44103087969","name":"Sabiedrība ar ierobežotu atbildību \"RG meistars\"","value":53267,"contracts":1,"singleBidRate":0}],"sharedOwnerGroups":[],"meta":{"coverage":"2023-10-25 … 2026-06-17","source":"IUB visa pieejamā vēsture","generatedAt":"2026-06-20T13:42:24.424Z","lots":67411,"buyers":916}}